static_node/__init__.py
static_node/cli.py
static_node/assets/example.txt
static_node-1.0.0.dist-info/LICENSE
static_node-1.0.0.dist-info/METADATA
static_node-1.0.0.dist-info/WHEEL
static_node-1.0.0.dist-info/entry_points.txt
static_node-1.0.0.dist-info/top_level.txt
static_node-1.0.0.dist-info/RECORD
