Metadata-Version: 2.1
Name: static-node
Version: 1.0.0
Summary: Node and NPM cross platform python install
Home-page: https://github.com/zackees/static-node
Maintainer: Zachary Vorhies
License: BSD 3-Clause License
Keywords: template-python-cmd
Classifier: Programming Language :: Python :: 3
Requires-Python: >=3.7
License-File: LICENSE
